nlsc/__init__.py
nlsc/__main__.py
nlsc/atomize.py
nlsc/cli.py
nlsc/diff.py
nlsc/emitter.py
nlsc/graph.py
nlsc/lockfile.py
nlsc/parser.py
nlsc/parser_treesitter.py
nlsc/resolver.py
nlsc/roundtrip.py
nlsc/schema.py
nlsc/sourcemap.py
nlsc/watch.py
nlsc/grammars/__init__.py
nlsc/grammars/nl.dll
nlsc/lsp/__init__.py
nlsc/lsp/analysis.py
nlsc/lsp/server.py
nlsc/resources/nls-file.ico
nlsc-0.2.4.dist-info/licenses/LICENSE
nlsc-0.2.4.dist-info/METADATA
nlsc-0.2.4.dist-info/WHEEL
nlsc-0.2.4.dist-info/entry_points.txt
nlsc-0.2.4.dist-info/top_level.txt
nlsc-0.2.4.dist-info/RECORD
