Metadata-Version: 2.4
Name: nlsc
Version: 0.2.4
Summary: Natural Language Source Compiler - Compile .nl specs to executable code
Author: Vario (Mnehmos)
License: MIT
Project-URL: Homepage, https://github.com/Mnehmos/mnehmos.nls.lang
Project-URL: Documentation, https://mnehmos.github.io/mnehmos.nls.lang/
Project-URL: Repository, https://github.com/Mnehmos/mnehmos.nls.lang
Keywords: natural-language,compiler,ai,code-generation
Classifier: Development Status :: 3 - Alpha
Classifier: Intended Audience :: Developers
Classifier: License :: OSI Approved :: MIT License
Classifier: Programming Language :: Python :: 3.11
Classifier: Programming Language :: Python :: 3.12
Classifier: Topic :: Software Development :: Compilers
Requires-Python: >=3.11
License-File: LICENSE
Requires-Dist: pyyaml>=6.0
Provides-Extra: dev
Requires-Dist: pytest>=7.0; extra == "dev"
Requires-Dist: pytest-cov>=4.0; extra == "dev"
Requires-Dist: hypothesis>=6.0; extra == "dev"
Requires-Dist: mypy>=1.0; extra == "dev"
Provides-Extra: llm
Requires-Dist: anthropic>=0.18.0; extra == "llm"
Requires-Dist: openai>=1.0; extra == "llm"
Provides-Extra: treesitter
Requires-Dist: tree-sitter>=0.23.0; extra == "treesitter"
Provides-Extra: lsp
Requires-Dist: pygls>=2.0.0; extra == "lsp"
Requires-Dist: lsprotocol>=2023.0.0; extra == "lsp"
Provides-Extra: docs
Requires-Dist: mkdocs>=1.5; extra == "docs"
Requires-Dist: mkdocs-material>=9.0; extra == "docs"
Requires-Dist: pymdown-extensions>=10.0; extra == "docs"
Dynamic: license-file
